multiples/__init__.py
multiples/is_multiple_of_five.py
multiples/is_multiple_of_two.py
tests/__init__.py
tests/test_is_multiple_of_five.py
tests/test_is_multiple_of_two.py
unique_multiples_library-0.1.0.dist-info/LICENSE.txt
unique_multiples_library-0.1.0.dist-info/METADATA
unique_multiples_library-0.1.0.dist-info/WHEEL
unique_multiples_library-0.1.0.dist-info/top_level.txt
unique_multiples_library-0.1.0.dist-info/RECORD
