Metadata-Version: 2.1
Name: unique-multiples-library
Version: 0.1.0
Summary: A library for checking multiples of 2 and 5.
Home-page: UNKNOWN
Author: Juhi Rastogi
Author-email: juhirastogi048@gmail.com
License: UNKNOWN
Platform: UNKNOWN
Classifier: Programming Language :: Python :: 3
Classifier: License :: OSI Approved :: MIT License
Classifier: Operating System :: OS Independent
Requires-Python: >=3.6
License-File: LICENSE.txt
